{
    "swagger": "2.0",
    "basePath": "/",
    "info": {
        "version": "0.0.1",
        "title": "bk-lesscode",
        "description": "bk-lesscode 对外接口"
    },
    "schemes": [
        "http"
    ],
    "paths": {
        "/dataManage": {
            "get": {
                "operationId": "dataManage",
                "description": "itsm 回调接口",
                "tags": [],
                "responses": {
                    "default": {
                        "description": ""
                    }
                },
                "x-bk-apigateway-resource": {
                    "isPublic": true,
                    "allowApplyPermission": true,
                    "matchSubpath": false,
                    "backend": {
                        "type": "HTTP",
                        "method": "post",
                        "path": "{env.subpath}/api/nocode/dataManage",
                        "matchSubpath": false,
                        "timeout": 0,
                        "upstreams": {},
                        "transformHeaders": {}
                    },
                    "authConfig": {
                        "userVerifiedRequired": false
                    },
                    "disabledStages": [],
                    "descriptionEn": null
                }
            }
        },
        "/filterTableData/keys/tableName/{tableName}": {
            "get": {
                "operationId": "filterTableDataByKeys",
                "description": "itsm 数据筛选接口",
                "tags": [],
                "responses": {
                    "default": {
                        "description": ""
                    }
                },
                "x-bk-apigateway-resource": {
                    "isPublic": true,
                    "allowApplyPermission": true,
                    "matchSubpath": false,
                    "backend": {
                        "type": "HTTP",
                        "method": "post",
                        "path": "{env.subpath}/api/nocode/filterTableData/keys/tableName/{tableName}",
                        "matchSubpath": false,
                        "timeout": 0,
                        "upstreams": {},
                        "transformHeaders": {}
                    },
                    "authConfig": {
                        "userVerifiedRequired": false
                    },
                    "disabledStages": [],
                    "descriptionEn": null
                }
            }
        },
        "/filterTableData/conditions/tableName/{tableName}": {
            "get": {
                "operationId": "filterTableDataByConditions",
                "description": "itsm 表单数据源",
                "tags": [],
                "responses": {
                    "default": {
                        "description": ""
                    }
                },
                "x-bk-apigateway-resource": {
                    "isPublic": true,
                    "allowApplyPermission": true,
                    "matchSubpath": false,
                    "backend": {
                        "type": "HTTP",
                        "method": "post",
                        "path": "{env.subpath}/api/nocode/filterTableData/conditions/tableName/{tableName}",
                        "matchSubpath": false,
                        "timeout": 0,
                        "upstreams": {},
                        "transformHeaders": {}
                    },
                    "authConfig": {
                        "userVerifiedRequired": false
                    },
                    "disabledStages": [],
                    "descriptionEn": null
                }
            }
        }
    }
}